paqlang/__init__.py
paqlang/_version.py
paqlang/aio_github.py
paqlang/aio_gitlab.py
paqlang/data.py
paqlang/param.py
paqlang/program.py
paqlang/utils.py
paqlang/ext/oracle_opers.py
paqlang/functions/bool_opers.py
paqlang/functions/control_opers.py
paqlang/functions/date_opers.py
paqlang/functions/dict_opers.py
paqlang/functions/github_opers.py
paqlang/functions/gitlab_opers.py
paqlang/functions/io_opers.py
paqlang/functions/math_opers.py
paqlang/functions/other_opers.py
paqlang/functions/queue_opers.py
paqlang/functions/string_opers.py
PAQLang-2.1.0.dist-info/LICENSE
PAQLang-2.1.0.dist-info/METADATA
PAQLang-2.1.0.dist-info/WHEEL
PAQLang-2.1.0.dist-info/top_level.txt
PAQLang-2.1.0.dist-info/RECORD
