Metadata-Version: 2.1
Name: PAQLang
Version: 2.1.0
Summary: Python Async Queue Language
Author-email: Sergey Strukov <strukovsv@main.ru>
Project-URL: Homepage, https://github.com/strukovsv/PAQLang
Project-URL: Issues, https://github.com/strukovsv/PAQLang/issues
Classifier: Development Status :: 4 - Beta
Classifier: Intended Audience :: Developers
Classifier: Topic :: Software Development :: Build Tools
Classifier: License :: OSI Approved :: MIT License
Classifier: Programming Language :: Python :: 3.11
Requires-Python: >=3.11
License-File: LICENSE
Requires-Dist: aiofiles ==23.2.1
Requires-Dist: PyYAML ==6.0.1
Requires-Dist: ruamel.yaml ==0.18.6
Requires-Dist: ruamel.yaml.clib ==0.2.8
Requires-Dist: ruamel.yaml.string ==0.1.1
Requires-Dist: requests ==2.31.0
Requires-Dist: boto3 ==1.34.54
Requires-Dist: environs ==9.5.0
Requires-Dist: httpx ==0.27.0
Requires-Dist: chardet ==5.2.0
Provides-Extra: oracle
Requires-Dist: cx-Oracle-async ==0.3.3 ; extra == 'oracle'
